{
    "original": {
        "text": "My uncle _Toby_ had scarce turned the corner of his yew hedge, which separated his kitchen-garden from his bowling-green, when he perceived the corporal had begun the attack without him.------\nLet me stop and give you a picture of the corporal's apparatus; and of the corporal himself in the height of his attack, just as it struck my uncle _Toby_, as he turned towards the sentry-box, where the corporal was at work, ----for in nature there is not such another, ----nor can any combination of all that is grotesque and whimsical in her works produce its equal.\nThe corporal------\n----Tread lightly on his ashes, ye men of genius, ----for he was your kinsman:\nWeed his grave clean, ye men of goodness, --for he was your brother. --Oh corporal! had I thee, but now, --now, that I am able to give thee a dinner and protection, --how would I cherish thee! thou should'st wear thy Montero-cap every hour of the day, and every day of the week, --and when it was worn out, I would purchase thee a couple like it: ----But alas! alas! alas! now that I can do this in spite of their reverences--the occasion is lost--for thou art gone; --thy genius fled up to the stars from whence it came; --and that warm heart of thine, with all its generous and open vessels, compressed into a _clod of the valley!_\n----But what----what is this, to that future and dreaded page, where I look towards the velvet pall, decorated with the military ensigns of thy master--the first--the foremost of created beings; ----where, I shall see thee, faithful servant! laying his sword and scabbard with a trembling hand across his coffin, and then returning pale as ashes to the door, to take his mourning horse by the bridle, to follow his hearse, as he directed thee; ----where--all my father's systems shall be baffled by his sorrows; and, in spite of his philosophy, I shall behold him, as he inspects the lackered plate, twice taking his spectacles from off his nose, to wipe away the dew which nature has shed upon them ----When I see him cast in the rosemary with an air of disconsolation, which cries through my ears, ----O _Toby!_ in what corner of the world shall I seek thy fellow?\n----Gracious powers! which erst have opened the lips of the dumb in his distress, and made the tongue of the stammerer speak plain----when I shall arrive at this dreaded page, deal not with me, then, with a stinted hand.",
        "paragraph_chars": [
            [
                0,
                193
            ],
            [
                193,
                562
            ],
            [
                562,
                581
            ],
            [
                581,
                660
            ],
            [
                660,
                1294
            ],
            [
                1294,
                2161
            ],
            [
                2161,
                2381
            ]
        ],
        "segment_chars": [
            [
                0,
                193
            ],
            [
                193,
                562
            ],
            [
                562,
                581
            ],
            [
                581,
                660
            ],
            [
                660,
                729
            ],
            [
                729,
                744
            ],
            [
                744,
                853
            ],
            [
                853,
                1021
            ],
            [
                1021,
                1027
            ],
            [
                1027,
                1033
            ],
            [
                1033,
                1294
            ],
            [
                1294,
                1536
            ],
            [
                1536,
                2161
            ],
            [
                2161,
                2182
            ],
            [
                2182,
                2381
            ]
        ],
        "overlap_chars": [
            [
                0,
                8
            ],
            [
                16,
                186
            ],
            [
                193,
                199
            ],
            [
                231,
                255
            ],
            [
                384,
                385
            ],
            [
                205,
                208
            ],
            [
                302,
                340
            ],
            [
                347,
                384
            ],
            [
                386,
                416
            ],
            [
                560,
                562
            ],
            [
                562,
                574
            ],
            [
                591,
                630
            ],
            [
                635,
                658
            ],
            [
                660,
                701
            ],
            [
                704,
                728
            ],
            [
                731,
                744
            ],
            [
                744,
                755
            ],
            [
                760,
                763
            ],
            [
                827,
                853
            ],
            [
                853,
                902
            ],
            [
                916,
                925
            ],
            [
                1011,
                1021
            ],
            [
                1021,
                1027
            ],
            [
                1117,
                1126
            ],
            [
                1129,
                1180
            ],
            [
                1184,
                1197
            ],
            [
                1236,
                1239
            ],
            [
                1227,
                1235
            ],
            [
                1198,
                1213
            ],
            [
                1254,
                1271
            ],
            [
                1273,
                1292
            ],
            [
                1298,
                1301
            ],
            [
                1310,
                1444
            ],
            [
                1446,
                1455
            ],
            [
                1470,
                1472
            ],
            [
                1493,
                1536
            ],
            [
                1536,
                1552
            ],
            [
                1566,
                1642
            ],
            [
                1698,
                1737
            ],
            [
                1742,
                1747
            ],
            [
                1749,
                1857
            ],
            [
                1894,
                1948
            ],
            [
                1661,
                1664
            ],
            [
                1998,
                2012
            ],
            [
                2013,
                2033
            ],
            [
                2098,
                2099
            ],
            [
                1653,
                1655
            ],
            [
                1680,
                1682
            ],
            [
                2105,
                2106
            ],
            [
                2108,
                2161
            ],
            [
                2165,
                2182
            ],
            [
                2182,
                2187
            ],
            [
                2205,
                2225
            ],
            [
                2241,
                2246
            ],
            [
                2266,
                2291
            ],
            [
                2295,
                2336
            ],
            [
                2351,
                2353
            ],
            [
                2355,
                2359
            ],
            [
                2380,
                2381
            ]
        ],
        "row_chars": [
            [
                0,
                193
            ],
            [
                193,
                562
            ],
            [
                562,
                581
            ],
            [
                581,
                660
            ],
            [
                660,
                729
            ],
            [
                729,
                744
            ],
            [
                744,
                853
            ],
            [
                853,
                1021
            ],
            [
                1021,
                1027
            ],
            [
                1027,
                1033
            ],
            [
                1033,
                1294
            ],
            [
                1294,
                1536
            ],
            [
                1536,
                2161
            ],
            [
                2161,
                2182
            ],
            [
                2182,
                2381
            ]
        ]
    },
    "abridged": {
        "text": "My uncle Toby had scarce turned the corner of his yew hedge, which separated his kitchen-garden from his bowling-green, when he perceived the corporal had begun the attack without him.\nLet me describe the corporal's apparatus, and his attack, just as it struck my uncle Toby, as he turned towards the sentry-box where the corporal was at work.\nThe corporal-\n- Tread lightly on his ashes, ye men of genius, for he was your kinsman.\nWeed his grave clean, ye men of goodness, for he was your brother.\nOh corporal! had I thee, now - how would I cherish thee! thou should'st wear thy Montero-cap every hour of every day - But alas! alas! thou art gone; thy genius fled up to the stars from whence it came - and that warm and generous heart of thine, compressed into a clod of the valley!\n- But what is this, to that future and dreaded page, where I look towards the velvet pall, decorated with the military ensigns of thy master - the first of men - where, I shall see thee, faithful servant! laying his sword with a trembling hand across his coffin, and then returning pale as ashes to follow his hearse, as he directed thee; where all my father's systems shall be baffled by his sorrows; and, in spite of his philosophy, I shall behold him twice taking his spectacles from off his nose, to wipe his eyes - when I see him sadly cast in the rosemary - O Toby! in what corner of the world shall I seek thy fellow?\nGracious powers! which open the lips of the dumb, and make the stammerer speak plain - when I shall arrive at this dreaded page, help me then.",
        "paragraph_chars": [
            [
                0,
                185
            ],
            [
                185,
                344
            ],
            [
                344,
                358
            ],
            [
                358,
                431
            ],
            [
                431,
                498
            ],
            [
                498,
                783
            ],
            [
                783,
                1408
            ],
            [
                1408,
                1550
            ]
        ],
        "segment_chars": [
            [
                0,
                185
            ],
            [
                185,
                344
            ],
            [
                344,
                358
            ],
            [
                358,
                431
            ],
            [
                431,
                498
            ],
            [
                498,
                511
            ],
            [
                511,
                555
            ],
            [
                555,
                627
            ],
            [
                627,
                633
            ],
            [
                633,
                783
            ],
            [
                783,
                988
            ],
            [
                988,
                1355
            ],
            [
                1355,
                1408
            ],
            [
                1408,
                1425
            ],
            [
                1425,
                1550
            ]
        ],
        "overlap_chars": [
            [
                0,
                8
            ],
            [
                14,
                184
            ],
            [
                185,
                191
            ],
            [
                201,
                225
            ],
            [
                225,
                226
            ],
            [
                227,
                230
            ],
            [
                231,
                269
            ],
            [
                274,
                311
            ],
            [
                312,
                342
            ],
            [
                342,
                344
            ],
            [
                344,
                356
            ],
            [
                366,
                405
            ],
            [
                406,
                429
            ],
            [
                431,
                472
            ],
            [
                473,
                497
            ],
            [
                498,
                511
            ],
            [
                511,
                522
            ],
            [
                523,
                526
            ],
            [
                529,
                555
            ],
            [
                555,
                604
            ],
            [
                605,
                614
            ],
            [
                617,
                627
            ],
            [
                627,
                633
            ],
            [
                638,
                647
            ],
            [
                648,
                699
            ],
            [
                702,
                715
            ],
            [
                716,
                719
            ],
            [
                720,
                728
            ],
            [
                729,
                744
            ],
            [
                745,
                762
            ],
            [
                763,
                782
            ],
            [
                785,
                788
            ],
            [
                789,
                923
            ],
            [
                926,
                935
            ],
            [
                936,
                938
            ],
            [
                945,
                988
            ],
            [
                988,
                1004
            ],
            [
                1005,
                1081
            ],
            [
                1082,
                1121
            ],
            [
                1122,
                1127
            ],
            [
                1128,
                1236
            ],
            [
                1237,
                1291
            ],
            [
                1292,
                1295
            ],
            [
                1303,
                1317
            ],
            [
                1324,
                1344
            ],
            [
                1347,
                1348
            ],
            [
                1349,
                1351
            ],
            [
                1351,
                1353
            ],
            [
                1353,
                1354
            ],
            [
                1355,
                1408
            ],
            [
                1408,
                1425
            ],
            [
                1425,
                1430
            ],
            [
                1436,
                1456
            ],
            [
                1456,
                1461
            ],
            [
                1467,
                1492
            ],
            [
                1495,
                1536
            ],
            [
                1542,
                1544
            ],
            [
                1545,
                1549
            ],
            [
                1549,
                1550
            ]
        ],
        "row_chars": [
            [
                0,
                185
            ],
            [
                185,
                344
            ],
            [
                344,
                358
            ],
            [
                358,
                431
            ],
            [
                431,
                498
            ],
            [
                498,
                511
            ],
            [
                511,
                555
            ],
            [
                555,
                627
            ],
            [
                627,
                633
            ],
            [
                633,
                633
            ],
            [
                633,
                783
            ],
            [
                783,
                988
            ],
            [
                988,
                1408
            ],
            [
                1408,
                1425
            ],
            [
                1425,
                1550
            ]
        ]
    }
}